easyvec/__init__.py
easyvec/geometry.cp39-win_amd64.pyd
easyvec/geometry.cpp
easyvec/geometry.pxd
easyvec/geometry.pyx
easyvec/matrixes.cp39-win_amd64.pyd
easyvec/matrixes.cpp
easyvec/matrixes.pxd
easyvec/matrixes.pyx
easyvec/vectors.cp39-win_amd64.pyd
easyvec/vectors.cpp
easyvec/vectors.html
easyvec/vectors.pxd
easyvec/vectors.pyx
easyvec-0.0.30.dist-info/LICENSE.txt
easyvec-0.0.30.dist-info/METADATA
easyvec-0.0.30.dist-info/WHEEL
easyvec-0.0.30.dist-info/top_level.txt
easyvec-0.0.30.dist-info/RECORD
